ignore/__init__.py
ignore/__init__.pyi
ignore/ignore.cpython-39-powerpc64le-linux-gnu.so
ignore/overrides/__init__.pyi
ignore/overrides/py.typed
ignore/py.typed
ignore_python-0.3.1.dist-info/METADATA
ignore_python-0.3.1.dist-info/WHEEL
ignore_python-0.3.1.dist-info/licenses/LICENSE.txt
ignore_python-0.3.1.dist-info/RECORD
