Metadata-Version: 2.4
Name: ignore-python
Version: 0.3.1
Classifier: Programming Language :: Rust
Classifier: Programming Language :: Python :: Implementation :: CPython
Classifier: Programming Language :: Python :: Implementation :: PyPy
License-File: LICENSE.txt
Summary: Rust ignore crate Python bindings
Keywords: python,gitignore,search,rust,extension,module,filesystem,recursively-search,fd,ripgrep,ignore
Requires-Python: >=3.8
Project-URL: documentation, https://borsattoz.github.io/ignore-python
Project-URL: repository, https://github.com/borsattoz/ignore-python
